rlotp/__init__.py
rlotp/compat.py
rlotp/hotp.py
rlotp/otp.py
rlotp/py.typed
rlotp/steam.py
rlotp/totp.py
rlotp/utils.py
rlotp/version.py
rlotp-0.0.8.dist-info/LICENSE
rlotp-0.0.8.dist-info/METADATA
rlotp-0.0.8.dist-info/WHEEL
rlotp-0.0.8.dist-info/top_level.txt
rlotp-0.0.8.dist-info/RECORD
