Metadata-Version: 2.1
Name: rlotp
Version: 0.0.8
Summary: Random Length OTP Library in Python
Home-page: https://github.com/rlotp/rlotp
Author: Md. Jahidul Hamid & PyOTP contributors
Author-email: jahidulhamid@yahoo.com
License: MIT License
Project-URL: Documentation, https://neurobin.github.io/rlotp
Project-URL: Source Code, https://github.com/neurobin/rlotp
Project-URL: Issue Tracker, https://github.com/neurobin/rlotp/issues
Project-URL: Change Log, https://github.com/neurobin/rlotp/blob/master/Changes.rst
Classifier: Intended Audience :: Developers
Classifier: License :: OSI Approved :: MIT License
Classifier: Programming Language :: Python
Classifier: Programming Language :: Python :: 3
Classifier: Programming Language :: Python :: 3.7
Classifier: Programming Language :: Python :: 3.8
Classifier: Programming Language :: Python :: 3.9
Classifier: Programming Language :: Python :: 3.10
Classifier: Programming Language :: Python :: 3.11
Classifier: Topic :: Software Development :: Libraries :: Python Modules
Requires-Python: >=3.7
License-File: LICENSE
